jdoff/__init__.py
jdoff-0.1.dist-info/METADATA
jdoff-0.1.dist-info/WHEEL
jdoff-0.1.dist-info/top_level.txt
jdoff-0.1.dist-info/RECORD
